passwort/__init__.py
passwort/__main__.py
passwort/tests/BasicTests.py
passwort/tests/__init__.py
passwort-1.1.3.dist-info/METADATA
passwort-1.1.3.dist-info/WHEEL
passwort-1.1.3.dist-info/entry_points.txt
passwort-1.1.3.dist-info/top_level.txt
passwort-1.1.3.dist-info/RECORD
