Metadata-Version: 2.4
Name: passwort
Version: 1.1.3
Summary: A simple password manager
Author-email: Lukhnos Liu <lukhnos@lukhnos.org>
License-Expression: MIT
Project-URL: Homepage, https://github.com/lukhnos/passwort
Requires-Dist: pwgen>=0.4
Requires-Dist: pycryptodomex>=3.6.1
